profiler/__init__.py
profiler/__version__.py
profiler-0.1.0.dist-info/DESCRIPTION.rst
profiler-0.1.0.dist-info/METADATA
profiler-0.1.0.dist-info/RECORD
profiler-0.1.0.dist-info/WHEEL
profiler-0.1.0.dist-info/metadata.json
profiler-0.1.0.dist-info/top_level.txt
