Metadata-Version: 2.0
Name: profiler
Version: 0.1.0
Summary: Simple tool to make profiling easy.
Home-page: https://github.com/bpabel/profiler
Author: Brendan Abel
Author-email: 007brendan@gmail.com
License: MIT
Platform: UNKNOWN
Classifier: License :: OSI Approved :: MIT License
Classifier: Programming Language :: Python
Classifier: Programming Language :: Python :: 2
Classifier: Programming Language :: Python :: 3
Classifier: Programming Language :: Python :: 3.6
Classifier: Programming Language :: Python :: Implementation :: CPython
Classifier: Programming Language :: Python :: Implementation :: PyPy
Requires-Python: >=2.7.0
